LICENSE
README.md
pyproject.toml
setup.py
src/jsonformatter/__init__.py
src/jsonformatter/jsonformatter.py
src/jsonformatter.egg-info/PKG-INFO
src/jsonformatter.egg-info/SOURCES.txt
src/jsonformatter.egg-info/dependency_links.txt
src/jsonformatter.egg-info/top_level.txt
tests/test.py
tests/test_windows.py