Metadata-Version: 2.1
Name: jsonformatter
Version: 0.3.3
Summary: Python log in json format.
Home-page: https://github.com/MyColorfulDays/jsonformatter.git
Author: MyColorfulDays
Author-email: MyColorfulDays <my_colorful_days@163.com>
License: BSD 2-Clause License
Project-URL: Homepage, https://github.com/MyColorfulDays/jsonformatter.git
Platform: all
Classifier: Development Status :: 2 - Pre-Alpha
Classifier: Intended Audience :: Developers
Classifier: License :: OSI Approved :: BSD License
Classifier: Operating System :: OS Independent
Classifier: Programming Language :: Python :: 2.7
Classifier: Programming Language :: Python :: 3
Classifier: Programming Language :: Python :: Implementation :: CPython
Classifier: Topic :: Utilities
Requires-Python: >=2.7
License-File: LICENSE
